neatpy/__init__.py
neatpy/activations.py
neatpy/brain.py
neatpy/draw.py
neatpy/genes.py
neatpy/innovation.py
neatpy/options.py
neatpy/population.py
neatpy/save.py
neatpy/species.py
neatpy-0.5.0.dist-info/LICENSE.md
neatpy-0.5.0.dist-info/METADATA
neatpy-0.5.0.dist-info/WHEEL
neatpy-0.5.0.dist-info/top_level.txt
neatpy-0.5.0.dist-info/RECORD
