Metadata-Version: 2.1
Name: neatpy
Version: 0.5.0
Summary: A NEAT library in Python
Home-page: https://github.com/reddragonnm/neatpy
Author: reddragonnm
License: MIT
Platform: UNKNOWN
